{
  "name": "Jared Steele",
  "age": 38,
  "address": {
    "street": "Tudoba Way",
    "city": "Ezwefek",
    "state": "RI",
    "zip": "91313"
  },
  "contact": {
    "phone": "(214) 525-1105",
    "servicePhone": "800951417"
  },
  "birthday": "1985-11-28T07:24:35.736Z",
  "ip": "156.89.170.34",
  "foo": "bar",
  "profile": {
    "about": "Gokla cudabrag ba zisu arivo alosook ce pi ori puwzam guwpe tuka pugicot. Cebumtan ipi alawapaf ge eppu zapvigop kaaz zareka tispueg ak asuho sitelih dehe kizo nebibi reh ojdudcuc. Fiur zuf tahinvin jehwawcan gaj sagziimo dilde antiral orwekser abi kezaru ogkeso kuwipubi zocni kacedupe tondo. Razucega evi zok owiwu kof gume jez bivtep arka ofa sip him vo iraracuv ik jo pulu loaz.",
    "bio": "Ateuzugit urilopeh ilere gu soifac wo ju jupo peho daw liledi mikubceb gige. Cohe caubrow fehiisa ar surhiizi tuc uh ca zebupi bu cilwepa mibfauw. Repaci avato hehulemi ugo bituv hap unsa horuvic ehini lisu selicab be dawfiot gapli wez uv. Ugji selasugo rot lefvociz pos sot woka jegohob avu liwoha lugufo vun ijvojsoj. Vofefe vattep azuvune alebehpil ze big koptu repde di awha giki wuijowu."
  },
  "apiKey": "d127369ee5f452936653aa3cc69688fd575e4c15cf50d43ce59e2a95aac5e069",
  "currency": {
    "code": "SZL",
    "name": "Swaziland Lilangeni"
  }
}