{
  "name": "Christina Craig",
  "age": 31,
  "address": {
    "street": "Omuto Heights",
    "city": "Ijiwanuw",
    "state": "FL",
    "zip": "97058"
  },
  "contact": {
    "phone": "(800) 245-5996",
    "servicePhone": "800613321"
  },
  "birthday": "1973-09-16T00:29:53.019Z",
  "ip": "87.56.119.72",
  "foo": "bar",
  "profile": {
    "about": "Migow ohidovi rap dosgu fedba jivle ohewirow azkafsi tumufo sific mu bu mazilbog moc johej. Naeto hi azaig ewara anocon areda te aze tuhogcot zomigi tobi imampib beohiad rihhup rekebza kizzose nasab obetogmep. Ava gudwaflu foulacur vedab bul gevdecu kulro gilohni cih dum de gipbor. Iwanewih baraese bo umauv wel viduwze fok fiov rijutage okuwu fidehufew bubge ra. Anreser kushuk no age zuhwel ul dembohom la naecpu nozna je luwridi has sa ara fun falgajic wolda.",
    "bio": "Kab uzibotop nunun penra ja gekdil bukoko juk heawa diwode gi newa roz pisfosim paphobsot. Rugdomu vop ru ma wew zisnuono rejloj pabobad anlat keguil golma diutizu hab ide re japdis berbinom. Zoama leselza biip une to ewehooh pu iwe tabi sulidem adooge afnebga ro tiz. Baj jihro sunizi pi zat tovvu vemak hacdav mo ese worde gu copus. Wuvatdi lorral nulu sodokum pot uf hawaz co hiir ipgemot mof ulu be zekoju azitow tip li tatlofi. Lubibo om esobajud nemouz unelago fe eb ceva saf pip gijkituk cirhaji rur lelogbuc avhoke riva ivsivug. Tu mitifan mad kala nuco gal fovabu hawieho fonta fevjitur jo zihdehcu ow."
  },
  "apiKey": "a5fef8318876c1767355be9c2a78406238c4e833e6ad960e5e6efd0e14232e28",
  "currency": {
    "code": "BIF",
    "name": "Burundi Franc"
  }
}